meh_calculator/__init__.py
meh_calculator/calculator.py
meh_calculator-1.1.0.dist-info/LICENSE
meh_calculator-1.1.0.dist-info/METADATA
meh_calculator-1.1.0.dist-info/WHEEL
meh_calculator-1.1.0.dist-info/top_level.txt
meh_calculator-1.1.0.dist-info/RECORD
