Metadata-Version: 2.1
Name: meh-calculator
Version: 1.1.0
Summary: A simple calculator for Mehedi
Author: Mehedi Mahmud
Author-email: 1001025@daffodil.ac
Classifier: Programming Language :: Python :: 3
Classifier: License :: OSI Approved :: MIT License
Classifier: Operating System :: OS Independent
License-File: LICENSE
